{
  "1826537": {
    "is_flagged": true,
    "remarks": [
      "pose_issue"
    ],
    "updated_at": "2025-12-02T15:06:41.611Z"
  },
  "1826539": {
    "is_flagged": true,
    "remarks": [
      "pose_issue"
    ],
    "updated_at": "2025-12-02T15:06:41.612Z"
  },
  "8409127": {
    "is_flagged": true,
    "remarks": [
      "pose_issue"
    ],
    "updated_at": "2025-12-02T15:02:53.931Z"
  },
  "15621488": {
    "is_flagged": true,
    "remarks": [
      "pose_issue"
    ],
    "updated_at": "2025-12-02T15:02:53.933Z"
  },
  "16070514": {
    "is_flagged": true,
    "remarks": [
      "pose_issue"
    ],
    "updated_at": "2025-12-02T15:02:53.933Z"
  }
}
